mkdocs_images_to_webp/__init__.py
mkdocs_images_to_webp/plugin.py
mkdocs_images_to_webp-0.11.dist-info/LICENSE
mkdocs_images_to_webp-0.11.dist-info/METADATA
mkdocs_images_to_webp-0.11.dist-info/WHEEL
mkdocs_images_to_webp-0.11.dist-info/entry_points.txt
mkdocs_images_to_webp-0.11.dist-info/top_level.txt
mkdocs_images_to_webp-0.11.dist-info/RECORD
